resourcesing/__init__.py
resourcesing-0.1.6.dist-info/METADATA
resourcesing-0.1.6.dist-info/WHEEL
resourcesing-0.1.6.dist-info/RECORD
